{
  "employees": [
    {
      "id": 2,
      "name": "Jordan Nelson"
    },
    {
      "id": 3,
      "name": "Zoe LeBlanc"
    },
    {
      "id": 4,
      "name": "Blaise Roberts"
    }
  ],
  "locations": [
    {
      "id": 1,
      "name": "Nashville North",
      "address": "500 Circle Way"
    },
    {
      "id": 2,
      "name": "Nashville South",
      "address": "10101 Binary Court"
    }
  ],
  "owners": [
    {
      "id": 1,
      "name": "Emma Beaton",
      "phone": "123-456-7890"
    },
    {
      "id": 2,
      "name": "Dani Adkins",
      "phone": "123-456-7890"
    },
    {
      "id": 3,
      "name": "Adam Oswalt",
      "phone": "123-456-7890"
    },
    {
      "id": 4,
      "name": "Fletcher Bangs",
      "phone": "123-456-7890"
    },
    {
      "id": 5,
      "name": "Emma Bennet",
      "phone": "123-456-7890"
    },
    {
      "id": 6,
      "name": "Ryan Tanay",
      "phone": "123-456-7890"
    }
  ],
  "animals": [
    {
      "id": 1,
      "name": "Jack",
      "owner": [
        1
      ]
    },{
      "id": 2,
      "name": "Boomer",
      "owner": [
        2
      ]
    },{
      "id": 3,
      "name": "Mick",
      "owner": [
        2
      ]
    },
    {
      "id": 4,
      "name": "Henley",
      "owner": [
        3,
        4
      ]
    },
    {
      "id": 5,
      "name": "Derkins",
      "owner": [
        5
      ]
    },
    {
      "id": 6,
      "name": "Checkers",
      "owner": [
        6
      ]
    }
  ]
}